structured_workouts/__init__.py
structured_workouts/base.py
structured_workouts/cli.py
structured_workouts/schema.py
structured_workouts/validation.py
structured_workouts/parsers/__init__.py
structured_workouts/parsers/base.py
structured_workouts/parsers/example_json_parser.py
structured_workouts/parsers/intervals_icu_api.py
structured_workouts/parsers/intervals_icu_text.py
structured_workouts-0.2.1.dist-info/METADATA
structured_workouts-0.2.1.dist-info/WHEEL
structured_workouts-0.2.1.dist-info/entry_points.txt
structured_workouts-0.2.1.dist-info/licenses/LICENSE
structured_workouts-0.2.1.dist-info/RECORD
