Metadata-Version: 2.4
Name: structured-workouts
Version: 0.2.1
Summary: A Python library for creating, parsing, and converting structured workout formats with support for parametrization.
Author-email: Aart Goossens <aart@sweatstack.no>
License-File: LICENSE
Requires-Python: >=3.12
Requires-Dist: pydantic>=2.0.0
